[{"RT":13841,"time": "2018-08-15 05:35:22pm", "schedule_type": "STATIC", "schedule_name": "random_1", "is_biased_choice":true,"side_choice": "RIGHT", "trial_number":0,"observed_reward":0,"unobserved_reward":1},{"RT":4656,"time": "2018-08-15 05:35:27pm", "schedule_type": "STATIC", "schedule_name": "random_1", "is_biased_choice":false,"side_choice": "LEFT", "trial_number":1,"observed_reward":0,"unobserved_reward":0},{"RT":4455,"time": "2018-08-15 05:35:32pm", "schedule_type": "STATIC", "schedule_name": "random_1", "is_biased_choice":true,"side_choice": "RIGHT", "trial_number":2,"observed_reward":0,"unobserved_reward":0},