[{"RT":4617,"time": "2018-08-15 01:43:12pm", "schedule_type": "STATIC", "schedule_name": "random_6", "is_biased_choice":true,"side_choice": "LEFT", "trial_number":0,"observed_reward":0,"unobserved_reward":0},{"RT":4792,"time": "2018-08-15 01:43:16pm", "schedule_type": "STATIC", "schedule_name": "random_6", "is_biased_choice":false,"side_choice": "RIGHT", "trial_number":1,"observed_reward":0,"unobserved_reward":1},{"RT":4056,"time": "2018-08-15 01:43:20pm", "schedule_type": "STATIC", "schedule_name": "random_6", "is_biased_choice":true,"side_choice": "LEFT", "trial_number":2,"observed_reward":0,"unobserved_reward":1},